[
  {
    "name": "Emery Reilly",
    "officeLocation": "California",
    "department": "Legal",
    "jobTitle": "Lawyer",
    "workPhone": "984-240-2223 x8209",
    "email": "Judge.Parker@hotmail.com",
    "image": "https://s3.amazonaws.com/uifaces/faces/twitter/balakayuriy/128.jpg"
  },
  {
    "name": "Raina Turcotte V",
    "officeLocation": "Boston",
    "department": "Services",
    "jobTitle": "Service Manager",
    "workPhone": "668.275.8586 x670",
    "email": "Rosalia_Jacobs8@gmail.com",
    "image": "https://s3.amazonaws.com/uifaces/faces/twitter/bluefx_/128.jpg"
  },
  {
    "name": "Maxime Metz",
    "officeLocation": "New York",
    "department": "Services",
    "jobTitle": "Service Manager",
    "workPhone": "1-144-016-8200 x497",
    "email": "Rigoberto_Will1@yahoo.com",
    "image": "https://s3.amazonaws.com/uifaces/faces/twitter/eduardostuart/128.jpg"
  },
  {
    "name": "Dr. Odessa Mosciski",
    "officeLocation": "New York",
    "department": "Legal",
    "jobTitle": "Lawyer",
    "workPhone": "(183) 270-4632 x9387",
    "email": "Tyrell_McKenzie42@gmail.com",
    "image": "https://s3.amazonaws.com/uifaces/faces/twitter/tom_even/128.jpg"
  },
  {
    "name": "Joelle Hoppe",
    "officeLocation": "Boston",
    "department": "Human Resources",
    "jobTitle": "Benefits Manager",
    "workPhone": "922-153-9890 x639",
    "email": "Charley69@gmail.com",
    "image": "https://s3.amazonaws.com/uifaces/faces/twitter/nfedoroff/128.jpg"
  },
  {
    "name": "Shad Hermiston",
    "officeLocation": "Boston",
    "department": "Human Resources",
    "jobTitle": "Benefits Manager",
    "workPhone": "298-466-2161 x5292",
    "email": "Devan8@hotmail.com",
    "image": "https://s3.amazonaws.com/uifaces/faces/twitter/HenryHoffman/128.jpg"
  },
  {
    "name": "Laila Wilkinson",
    "officeLocation": "California",
    "department": "Marketing",
    "jobTitle": "Marketing Analyst",
    "workPhone": "826.665.8568",
    "email": "Eden0@hotmail.com",
    "image": "https://s3.amazonaws.com/uifaces/faces/twitter/gavr1l0/128.jpg"
  },
  {
    "name": "Mortimer Wilkinson",
    "officeLocation": "New York",
    "department": "Services",
    "jobTitle": "Service Manager",
    "workPhone": "(901) 637-4674 x52940",
    "email": "Emmalee_Okuneva61@yahoo.com",
    "image": "https://s3.amazonaws.com/uifaces/faces/twitter/terpimost/128.jpg"
  },
  {
    "name": "Tabitha Ernser",
    "officeLocation": "Florida",
    "department": "Legal",
    "jobTitle": "Lawyer",
    "workPhone": "550-261-2374",
    "email": "Alphonso.Legros@yahoo.com",
    "image": "https://s3.amazonaws.com/uifaces/faces/twitter/linux29/128.jpg"
  },
  {
    "name": "Marietta Herzog",
    "officeLocation": "Boston",
    "department": "Services",
    "jobTitle": "Service Manager",
    "workPhone": "(809) 986-3470",
    "email": "Lavern40@yahoo.com",
    "image": "https://s3.amazonaws.com/uifaces/faces/twitter/petar_prog/128.jpg"
  },
  {
    "name": "Meggie Skiles",
    "officeLocation": "California",
    "department": "Legal",
    "jobTitle": "Lawyer",
    "workPhone": "1-470-409-6088 x322",
    "email": "Lonzo_Herzog60@gmail.com",
    "image": "https://s3.amazonaws.com/uifaces/faces/twitter/jitachi/128.jpg"
  },
  {
    "name": "Fanny McCullough Sr.",
    "officeLocation": "Ohio",
    "department": "Human Resources",
    "jobTitle": "Benefits Manager",
    "workPhone": "(894) 790-2008 x479",
    "email": "Kaitlin27@yahoo.com",
    "image": "https://s3.amazonaws.com/uifaces/faces/twitter/mcflydesign/128.jpg"
  },
  {
    "name": "Micah Leannon IV",
    "officeLocation": "Ohio",
    "department": "Human Resources",
    "jobTitle": "Benefits Manager",
    "workPhone": "886.146.2129 x41907",
    "email": "Carmine.Emmerich@hotmail.com",
    "image": "https://s3.amazonaws.com/uifaces/faces/twitter/thimo_cz/128.jpg"
  },
  {
    "name": "Jaylan Crona",
    "officeLocation": "New York",
    "department": "Sales",
    "jobTitle": "Sales Rep",
    "workPhone": "(339) 062-6448",
    "email": "Zakary78@yahoo.com",
    "image": "https://s3.amazonaws.com/uifaces/faces/twitter/attacks/128.jpg"
  },
  {
    "name": "Kip Morissette",
    "officeLocation": "Florida",
    "department": "Sales",
    "jobTitle": "Sales Rep",
    "workPhone": "163-341-9143",
    "email": "Aliza.Watsica35@gmail.com",
    "image": "https://s3.amazonaws.com/uifaces/faces/twitter/curiousoffice/128.jpg"
  },
  {
    "name": "Isaias Bartell",
    "officeLocation": "Boston",
    "department": "Marketing",
    "jobTitle": "Marketing Analyst",
    "workPhone": "(666) 520-4096 x363",
    "email": "Cassie.Bernier36@gmail.com",
    "image": "https://s3.amazonaws.com/uifaces/faces/twitter/sprayaga/128.jpg"
  },
  {
    "name": "Abbie Becker",
    "officeLocation": "California",
    "department": "Sales",
    "jobTitle": "Sales Rep",
    "workPhone": "1-239-466-9969",
    "email": "Phoebe90@yahoo.com",
    "image": "https://s3.amazonaws.com/uifaces/faces/twitter/andresdjasso/128.jpg"
  },
  {
    "name": "Dr. Kailee Bayer",
    "officeLocation": "Florida",
    "department": "Sales",
    "jobTitle": "Sales Rep",
    "workPhone": "(201) 460-2655",
    "email": "William45@yahoo.com",
    "image": "https://s3.amazonaws.com/uifaces/faces/twitter/kkusaa/128.jpg"
  },
  {
    "name": "Ramiro Sawayn",
    "officeLocation": "New York",
    "department": "Human Resources",
    "jobTitle": "Benefits Manager",
    "workPhone": "1-824-754-1793",
    "email": "Lane_Brekke@gmail.com",
    "image": "https://s3.amazonaws.com/uifaces/faces/twitter/gabrielrosser/128.jpg"
  },
  {
    "name": "Rod Flatley",
    "officeLocation": "Boston",
    "department": "Services",
    "jobTitle": "Service Manager",
    "workPhone": "673-698-9182 x0675",
    "email": "Sigmund.Rowe20@yahoo.com",
    "image": "https://s3.amazonaws.com/uifaces/faces/twitter/gofrasdesign/128.jpg"
  },
  {
    "name": "Mattie Schinner",
    "officeLocation": "Florida",
    "department": "Marketing",
    "jobTitle": "Marketing Analyst",
    "workPhone": "332-354-7235 x69749",
    "email": "Assunta.Pouros@gmail.com",
    "image": "https://s3.amazonaws.com/uifaces/faces/twitter/grahamkennery/128.jpg"
  },
  {
    "name": "Karelle Hand",
    "officeLocation": "Florida",
    "department": "Services",
    "jobTitle": "Service Manager",
    "workPhone": "(995) 721-6038",
    "email": "Sidney.Koepp19@yahoo.com",
    "image": "https://s3.amazonaws.com/uifaces/faces/twitter/yayteejay/128.jpg"
  },
  {
    "name": "Rosetta Franecki",
    "officeLocation": "Ohio",
    "department": "Legal",
    "jobTitle": "Lawyer",
    "workPhone": "(959) 181-3692",
    "email": "Estelle_Bode44@hotmail.com",
    "image": "https://s3.amazonaws.com/uifaces/faces/twitter/danro/128.jpg"
  },
  {
    "name": "Trenton Farrell",
    "officeLocation": "New York",
    "department": "Sales",
    "jobTitle": "Sales Rep",
    "workPhone": "1-364-649-8397",
    "email": "Carmela.Rice@gmail.com",
    "image": "https://s3.amazonaws.com/uifaces/faces/twitter/yayteejay/128.jpg"
  },
  {
    "name": "Georgette Botsford III",
    "officeLocation": "California",
    "department": "Services",
    "jobTitle": "Service Manager",
    "workPhone": "904-289-4977 x12158",
    "email": "Nat.Simonis@gmail.com",
    "image": "https://s3.amazonaws.com/uifaces/faces/twitter/osmond/128.jpg"
  },
  {
    "name": "Jeanie Hyatt",
    "officeLocation": "Ohio",
    "department": "Sales",
    "jobTitle": "Sales Rep",
    "workPhone": "788-180-5442",
    "email": "Drew_Casper86@yahoo.com",
    "image": "https://s3.amazonaws.com/uifaces/faces/twitter/doronmalki/128.jpg"
  },
  {
    "name": "Cristal Keeling",
    "officeLocation": "Ohio",
    "department": "Human Resources",
    "jobTitle": "Benefits Manager",
    "workPhone": "(721) 028-4139",
    "email": "Boris96@hotmail.com",
    "image": "https://s3.amazonaws.com/uifaces/faces/twitter/leonfedotov/128.jpg"
  },
  {
    "name": "Adrain Watsica",
    "officeLocation": "Ohio",
    "department": "Human Resources",
    "jobTitle": "Benefits Manager",
    "workPhone": "(942) 263-3666",
    "email": "Leif_Reilly@hotmail.com",
    "image": "https://s3.amazonaws.com/uifaces/faces/twitter/petar_prog/128.jpg"
  },
  {
    "name": "Della Miller",
    "officeLocation": "Florida",
    "department": "Legal",
    "jobTitle": "Lawyer",
    "workPhone": "(555) 367-6347",
    "email": "Tyreek_Heidenreich37@gmail.com",
    "image": "https://s3.amazonaws.com/uifaces/faces/twitter/jm_denis/128.jpg"
  },
  {
    "name": "Kyler Goyette",
    "officeLocation": "New York",
    "department": "Marketing",
    "jobTitle": "Marketing Analyst",
    "workPhone": "695.444.6802 x677",
    "email": "Hardy.Hane46@hotmail.com",
    "image": "https://s3.amazonaws.com/uifaces/faces/twitter/cynthiasavard/128.jpg"
  },
  {
    "name": "Chadd Rutherford I",
    "officeLocation": "California",
    "department": "Marketing",
    "jobTitle": "Marketing Analyst",
    "workPhone": "1-392-333-1984 x8097",
    "email": "Trever.Hackett@hotmail.com",
    "image": "https://s3.amazonaws.com/uifaces/faces/twitter/imcoding/128.jpg"
  },
  {
    "name": "Magnus Kutch",
    "officeLocation": "Boston",
    "department": "Services",
    "jobTitle": "Service Manager",
    "workPhone": "227-552-7179",
    "email": "Aron_Hermiston0@hotmail.com",
    "image": "https://s3.amazonaws.com/uifaces/faces/twitter/privetwagner/128.jpg"
  },
  {
    "name": "Sienna Kilback",
    "officeLocation": "New York",
    "department": "Services",
    "jobTitle": "Service Manager",
    "workPhone": "1-757-492-1586 x434",
    "email": "Ariane.Smitham91@yahoo.com",
    "image": "https://s3.amazonaws.com/uifaces/faces/twitter/enjoythetau/128.jpg"
  },
  {
    "name": "Ella Moen",
    "officeLocation": "Florida",
    "department": "Sales",
    "jobTitle": "Sales Rep",
    "workPhone": "1-499-505-0377 x289",
    "email": "Ella_Murazik@hotmail.com",
    "image": "https://s3.amazonaws.com/uifaces/faces/twitter/jonsgotwood/128.jpg"
  },
  {
    "name": "Marlee Kemmer",
    "officeLocation": "Florida",
    "department": "Human Resources",
    "jobTitle": "Benefits Manager",
    "workPhone": "198-944-9251 x754",
    "email": "Raymundo.Hudson@yahoo.com",
    "image": "https://s3.amazonaws.com/uifaces/faces/twitter/rpeezy/128.jpg"
  },
  {
    "name": "George Kassulke",
    "officeLocation": "Florida",
    "department": "Marketing",
    "jobTitle": "Marketing Analyst",
    "workPhone": "(219) 281-0433 x3457",
    "email": "Candida.Jenkins@hotmail.com",
    "image": "https://s3.amazonaws.com/uifaces/faces/twitter/theonlyzeke/128.jpg"
  },
  {
    "name": "Louisa Davis",
    "officeLocation": "Boston",
    "department": "Legal",
    "jobTitle": "Lawyer",
    "workPhone": "(524) 059-5125 x787",
    "email": "Dax_Okuneva@hotmail.com",
    "image": "https://s3.amazonaws.com/uifaces/faces/twitter/belyaev_rs/128.jpg"
  },
  {
    "name": "Daniela Kuhn V",
    "officeLocation": "Florida",
    "department": "Marketing",
    "jobTitle": "Marketing Analyst",
    "workPhone": "032-558-8249 x1536",
    "email": "Elyse.Abernathy@hotmail.com",
    "image": "https://s3.amazonaws.com/uifaces/faces/twitter/xravil/128.jpg"
  },
  {
    "name": "Nya Fadel",
    "officeLocation": "New York",
    "department": "Services",
    "jobTitle": "Service Manager",
    "workPhone": "541.626.7487 x76849",
    "email": "Carlotta.Jakubowski30@gmail.com",
    "image": "https://s3.amazonaws.com/uifaces/faces/twitter/sircalebgrove/128.jpg"
  },
  {
    "name": "Aracely Torp",
    "officeLocation": "Boston",
    "department": "Sales",
    "jobTitle": "Sales Rep",
    "workPhone": "898-684-1921",
    "email": "Amya_Schuppe@hotmail.com",
    "image": "https://s3.amazonaws.com/uifaces/faces/twitter/ostirbu/128.jpg"
  },
  {
    "name": "Naomi Boyle",
    "officeLocation": "California",
    "department": "Services",
    "jobTitle": "Service Manager",
    "workPhone": "433-358-6584",
    "email": "Esta53@gmail.com",
    "image": "https://s3.amazonaws.com/uifaces/faces/twitter/sta1ex/128.jpg"
  },
  {
    "name": "Pascale Bahringer",
    "officeLocation": "New York",
    "department": "Services",
    "jobTitle": "Service Manager",
    "workPhone": "1-160-121-9598 x14229",
    "email": "Zachery_Torp22@gmail.com",
    "image": "https://s3.amazonaws.com/uifaces/faces/twitter/paulfarino/128.jpg"
  },
  {
    "name": "Sidney Runte",
    "officeLocation": "Florida",
    "department": "Services",
    "jobTitle": "Service Manager",
    "workPhone": "002-841-3046 x4156",
    "email": "Jade.Swaniawski@gmail.com",
    "image": "https://s3.amazonaws.com/uifaces/faces/twitter/vickyshits/128.jpg"
  },
  {
    "name": "Darrell Hermann",
    "officeLocation": "New York",
    "department": "Sales",
    "jobTitle": "Sales Rep",
    "workPhone": "378.749.2941 x8448",
    "email": "Sheldon.Smith88@gmail.com",
    "image": "https://s3.amazonaws.com/uifaces/faces/twitter/mr_shiznit/128.jpg"
  },
  {
    "name": "Carmela Donnelly",
    "officeLocation": "New York",
    "department": "Sales",
    "jobTitle": "Sales Rep",
    "workPhone": "1-900-844-8217 x037",
    "email": "Christa.Herzog75@yahoo.com",
    "image": "https://s3.amazonaws.com/uifaces/faces/twitter/jffgrdnr/128.jpg"
  },
  {
    "name": "Danika Breitenberg",
    "officeLocation": "California",
    "department": "Sales",
    "jobTitle": "Sales Rep",
    "workPhone": "548-235-4839",
    "email": "Mary33@gmail.com",
    "image": "https://s3.amazonaws.com/uifaces/faces/twitter/zvchkelly/128.jpg"
  },
  {
    "name": "Mr. Flo Metz",
    "officeLocation": "New York",
    "department": "Legal",
    "jobTitle": "Lawyer",
    "workPhone": "352.282.0372 x7447",
    "email": "Gerard.Schamberger@yahoo.com",
    "image": "https://s3.amazonaws.com/uifaces/faces/twitter/madebybrenton/128.jpg"
  },
  {
    "name": "Noemy Lind",
    "officeLocation": "Ohio",
    "department": "Human Resources",
    "jobTitle": "Benefits Manager",
    "workPhone": "240-003-9896",
    "email": "Melyna_Hayes18@hotmail.com",
    "image": "https://s3.amazonaws.com/uifaces/faces/twitter/byryan/128.jpg"
  },
  {
    "name": "Morris Crona Sr.",
    "officeLocation": "New York",
    "department": "Human Resources",
    "jobTitle": "Benefits Manager",
    "workPhone": "(948) 774-5087 x673",
    "email": "Arnulfo63@gmail.com",
    "image": "https://s3.amazonaws.com/uifaces/faces/twitter/juaumlol/128.jpg"
  },
  {
    "name": "Pascale Bartell",
    "officeLocation": "New York",
    "department": "Legal",
    "jobTitle": "Lawyer",
    "workPhone": "(678) 589-1311 x62213",
    "email": "Norwood_Ryan20@yahoo.com",
    "image": "https://s3.amazonaws.com/uifaces/faces/twitter/justinrhee/128.jpg"
  },
  {
    "name": "Judge Balistreri",
    "officeLocation": "Florida",
    "department": "Marketing",
    "jobTitle": "Marketing Analyst",
    "workPhone": "442.376.5122 x998",
    "email": "Mikayla_Champlin42@hotmail.com",
    "image": "https://s3.amazonaws.com/uifaces/faces/twitter/brajeshwar/128.jpg"
  },
  {
    "name": "Elisa Okuneva",
    "officeLocation": "Ohio",
    "department": "Sales",
    "jobTitle": "Sales Rep",
    "workPhone": "828-571-7040 x24045",
    "email": "Angel_Sporer66@hotmail.com",
    "image": "https://s3.amazonaws.com/uifaces/faces/twitter/madcampos/128.jpg"
  },
  {
    "name": "Colin Kuhlman",
    "officeLocation": "California",
    "department": "Sales",
    "jobTitle": "Sales Rep",
    "workPhone": "(183) 752-0195 x424",
    "email": "Joshuah26@hotmail.com",
    "image": "https://s3.amazonaws.com/uifaces/faces/twitter/imsoper/128.jpg"
  },
  {
    "name": "Demetris Stracke",
    "officeLocation": "New York",
    "department": "Sales",
    "jobTitle": "Sales Rep",
    "workPhone": "(655) 441-6356 x907",
    "email": "Lue47@yahoo.com",
    "image": "https://s3.amazonaws.com/uifaces/faces/twitter/leandrovaranda/128.jpg"
  },
  {
    "name": "Franco Wisoky IV",
    "officeLocation": "Florida",
    "department": "Marketing",
    "jobTitle": "Marketing Analyst",
    "workPhone": "037-286-2271 x642",
    "email": "Mustafa_Quigley43@hotmail.com",
    "image": "https://s3.amazonaws.com/uifaces/faces/twitter/nastya_mane/128.jpg"
  },
  {
    "name": "Hannah Walter",
    "officeLocation": "Boston",
    "department": "Legal",
    "jobTitle": "Lawyer",
    "workPhone": "(308) 329-8846",
    "email": "Gust_Jacobson24@hotmail.com",
    "image": "https://s3.amazonaws.com/uifaces/faces/twitter/Shriiiiimp/128.jpg"
  },
  {
    "name": "Brain Collier",
    "officeLocation": "California",
    "department": "Human Resources",
    "jobTitle": "Benefits Manager",
    "workPhone": "(623) 182-6007 x30052",
    "email": "Shayne.Erdman@gmail.com",
    "image": "https://s3.amazonaws.com/uifaces/faces/twitter/allthingssmitty/128.jpg"
  },
  {
    "name": "Elwin Stehr",
    "officeLocation": "Boston",
    "department": "Sales",
    "jobTitle": "Sales Rep",
    "workPhone": "718-469-5829 x79244",
    "email": "Berniece_Ernser@yahoo.com",
    "image": "https://s3.amazonaws.com/uifaces/faces/twitter/haligaliharun/128.jpg"
  },
  {
    "name": "Mathew Mills",
    "officeLocation": "Boston",
    "department": "Marketing",
    "jobTitle": "Marketing Analyst",
    "workPhone": "631-782-4863 x7165",
    "email": "Damion.Yundt46@yahoo.com",
    "image": "https://s3.amazonaws.com/uifaces/faces/twitter/oskamaya/128.jpg"
  },
  {
    "name": "Della Witting",
    "officeLocation": "New York",
    "department": "Human Resources",
    "jobTitle": "Benefits Manager",
    "workPhone": "416.953.5497 x0269",
    "email": "Lincoln.MacGyver10@yahoo.com",
    "image": "https://s3.amazonaws.com/uifaces/faces/twitter/nelsonjoyce/128.jpg"
  },
  {
    "name": "Colin Waters",
    "officeLocation": "Florida",
    "department": "Marketing",
    "jobTitle": "Marketing Analyst",
    "workPhone": "(192) 770-6368",
    "email": "Elwin_Miller@hotmail.com",
    "image": "https://s3.amazonaws.com/uifaces/faces/twitter/jesseddy/128.jpg"
  }
]
